{
  "name": "清",
  "children": [
    {
      "name": "仲",
      "children": [
        {
          "name": "玘",
          "children": [
            {
              "name": "洪",
              "children": [
                {
                  "name": "秋"
                },
                {
                  "name": "林"
                },
                {
                  "name": "文",
                  "children": [
                    {
                      "name": "景辉",
                      "children": [
                        {
                          "name": "立本",
                          "children": [
                            {
                              "name": "思问"
                            }
                          ]
                        }
                      ]
                    }
                  ]
                },
                {
                  "name": "章"
                },
                {
                  "name": "策"
                }
              ]
            },
            {
              "name": "河"
            },
            {
              "name": "潭"
            },
            {
              "name": "铎"
            }
          ]
        }
      ]
    }
  ]
}